pydreamplet/__init__.py
pydreamplet/colors.py
pydreamplet/core.py
pydreamplet/markers.py
pydreamplet/math.py
pydreamplet/noise.py
pydreamplet/scales.py
pydreamplet/shapes.py
pydreamplet/typography.py
pydreamplet/utils.py
pydreamplet/resources/__init__.py
pydreamplet/py.typed
pydreamplet/resources/hummingbird.svg
pydreamplet/resources/world_map_iso2.svg
pydreamplet/resources/world_map_iso3.svg
pydreamplet-1.1.10.dist-info/METADATA
pydreamplet-1.1.10.dist-info/WHEEL
pydreamplet-1.1.10.dist-info/licenses/LICENSE
pydreamplet-1.1.10.dist-info/RECORD
