Metadata-Version: 2.4
Name: pydreamplet
Version: 1.1.10
Summary: A versatile Python toolkit for programmatically generating, manipulating, and assembling scalable vector graphics (SVG) images.
Project-URL: Documentation, https://marepilc.github.io/pydreamplet/
Project-URL: Homepage, https://marepilc.github.io/pydreamplet/
Project-URL: Repository, https://github.com/marepilc/pydreamplet
Project-URL: Source Code, https://github.com/marepilc/pydreamplet
Author-email: Marek Pilczuk <user@mp76.pl>
License-Expression: MIT
License-File: LICENSE
Keywords: design,graphics,svg
Requires-Python: >=3.12
Requires-Dist: fonttools<5.0.0,>=4.56.0
Requires-Dist: ipykernel>=6.30.1
Requires-Dist: ipython<9.0.0,>=8.32.0
Requires-Dist: pillow<12.0.0,>=11.1.0
Provides-Extra: dev
Requires-Dist: jupyter>=1.1.1; extra == 'dev'
Requires-Dist: mkdocs-material>=9.6.4; extra == 'dev'
Requires-Dist: pytest>=8.4.1; extra == 'dev'
Requires-Dist: ruff>=0.9.5; extra == 'dev'
